{
  "model":"Collection<io.alkapivo.visu.editor.api.VEBrushTemplate>",
  "version":"1",
  "data":[
    {
      "type":"brush_view_config",
      "color":"#26FF00",
      "texture":"texture_visu_editor_icon_event_view_config",
      "properties":{
        "view-config_use-render-particles":0.0,
        "view-config_use-render-video":1.0,
        "view-config_render-particles":0.0,
        "view-config_use-transform-particles-z":0.0,
        "view-config_render-video":1.0,
        "view-config_transform-particles-z":{
          "startValue":0.0,
          "finished":0.0,
          "target":1.0,
          "factor":0.01,
          "increase":0.0,
          "value":0.0
        }
      },
      "name":"render video ON"
    },
    {
      "type":"brush_view_config",
      "color":"#FF2800",
      "texture":"texture_visu_editor_icon_event_view_config",
      "properties":{
        "view-config_use-render-particles":0.0,
        "view-config_use-render-video":1.0,
        "view-config_render-particles":0.0,
        "view-config_use-transform-particles-z":0.0,
        "view-config_render-video":0.0,
        "view-config_transform-particles-z":{
          "startValue":0.0,
          "finished":0.0,
          "target":1.0,
          "factor":0.01,
          "increase":0.0,
          "value":0.0
        }
      },
      "name":"render video OFF"
    },
    {
      "type":"brush_view_config",
      "color":"#5BD908",
      "texture":"texture_visu_editor_icon_event_view_config",
      "properties":{
        "view-config_use-render-particles":1.0,
        "view-config_use-render-video":0.0,
        "view-config_render-particles":1.0,
        "view-config_use-transform-particles-z":0.0,
        "view-config_render-video":1.0,
        "view-config_transform-particles-z":{
          "startValue":0.0,
          "finished":0.0,
          "target":1.0,
          "factor":0.01,
          "increase":0.0,
          "value":0.0
        }
      },
      "name":"render particles ON"
    },
    {
      "type":"brush_view_config",
      "color":"#FF2859",
      "texture":"texture_visu_editor_icon_event_view_config",
      "properties":{
        "view-config_use-render-particles":1.0,
        "view-config_use-render-video":0.0,
        "view-config_render-particles":0.0,
        "view-config_use-transform-particles-z":0.0,
        "view-config_render-video":1.0,
        "view-config_transform-particles-z":{
          "startValue":0.0,
          "finished":0.0,
          "target":1.0,
          "factor":0.01,
          "increase":0.0,
          "value":0.0
        }
      },
      "name":"render particles OFF"
    },
    {
      "type":"brush_view_config",
      "color":"#00FF00",
      "texture":"texture_visu_editor_icon_event_view_config",
      "properties":{
        "view-config_use-render-particles":0.0,
        "view-config_use-render-video":0.0,
        "view-config_use-transform-particles-z":0.0,
        "view-config_bkt-config":"easy",
        "view-config_bkt-factor":0.01,
        "view-config_bkt-trigger":false,
        "view-config_bkt-use-config":false,
        "view-config_bkt-use-factor":true,
        "view-config_render-particles":1.0,
        "view-config_render-video":1.0,
        "view-config_transform-particles-z":{
          "startValue":0.0,
          "finished":false,
          "target":1.0,
          "factor":999.0,
          "increase":0.0,
          "value":0.0
        }
      },
      "name":"BTKGlitch 1"
    },
    {
      "type":"brush_view_config",
      "color":"#961AFF",
      "texture":"texture_visu_editor_icon_event_view_config",
      "properties":{
        "view-config_use-render-particles":0.0,
        "view-config_use-render-video":0.0,
        "view-config_use-transform-particles-z":0.0,
        "view-config_bkt-config":"easy",
        "view-config_bkt-factor":0.0035999999999999999,
        "view-config_bkt-trigger":1.0,
        "view-config_bkt-use-config":0.0,
        "view-config_bkt-use-factor":1.0,
        "view-config_render-particles":0.0,
        "view-config_render-video":1.0,
        "view-config_transform-particles-z":{
          "startValue":0.0,
          "finished":0.0,
          "target":1.0,
          "factor":0.01,
          "increase":0.0,
          "value":0.0
        }
      },
      "name":"BTKGlitch 2"
    }
  ]
}