{
  "version":"1",
  "data":[
    {
      "color":"#FF0000",
      "type":"brush_shroom_clear",
      "properties":{
        "shroom-clear_clear-amount":1.0,
        "shroom-clear_use-clear-all-shrooms":1.0,
        "shroom-clear_use-clear-amount":0.0
      },
      "texture":"texture_ve_icon_entity",
      "name":"clear all"
    },
    {
      "color":"#FFDF43",
      "type":"brush_shroom_clear",
      "properties":{
        "shroom-clear_clear-amount":1.0,
        "shroom-clear_use-clear-all-shrooms":0.0,
        "shroom-clear_use-clear-amount":1.0
      },
      "texture":"texture_ve_icon_entity",
      "name":"clear 1"
    }
  ],
  "model":"Collection<io.alkapivo.visu.editor.api.VEBrushTemplate>"
}