{
  "model":"Collection<io.alkapivo.core.service.texture.TextureIntent>",
  "data":{
    "texture_lolratz_saycheese":{
      "frames":1.0,
      "prefetch":1.0,
      "file":"saycheese.png",
      "originX":0.0,
      "originY":0.0,
      "name":"texture_lolratz_saycheese"
    },
    "texture_lolratz_kaideca_obey":{
      "frames":1.0,
      "prefetch":1.0,
      "file":"kaideca-obey.png",
      "originX":0.0,
      "originY":0.0,
      "name":"texture_lolratz_kaideca_obey"
    },
    "texture_lolratz_tomo_emoji":{
      "frames":1.0,
      "prefetch":1.0,
      "file":"1228260015316406302.png",
      "originX":0.0,
      "originY":0.0,
      "name":"texture_lolratz_tomo_emoji"
    },
    "texture_lolratz_lime":{
      "frames":1.0,
      "prefetch":1.0,
      "file":"spoiler_image.png",
      "originX":0.0,
      "originY":0.0,
      "name":"texture_lolratz_lime"
    },
    "texture_lolratz_tomo_realgirl":{
      "frames":1.0,
      "prefetch":1.0,
      "file":"spoiler_realgirl.png",
      "originX":0.0,
      "originY":0.0,
      "name":"texture_lolratz_tomo_realgirl"
    },
    "texture_lolratz_heart_1":{
      "frames":3.0,
      "prefetch":1.0,
      "file":"Sprite68_strip3.png",
      "originX":0.0,
      "originY":0.0,
      "name":"texture_lolratz_heart_1"
    },
    "texture_lolratz_14266754a":{
      "frames":1.0,
      "prefetch":1.0,
      "file":"14266754a.png",
      "originX":0.0,
      "originY":0.0,
      "name":"texture_lolratz_14266754a"
    },
    "texture_lolratz_spot":{
      "frames":1.0,
      "prefetch":1.0,
      "file":"spot.png",
      "originX":0.0,
      "originY":0.0,
      "name":"texture_lolratz_spot"
    },
    "texture_lolratz_404":{
      "frames":1.0,
      "prefetch":1.0,
      "file":"404.png",
      "originX":0.0,
      "originY":0.0,
      "name":"texture_lolratz_404"
    },
    "texture_lolratz_takes_a_ride":{
      "frames":1.0,
      "prefetch":1.0,
      "file":"lolratz_takes_a_ride.png",
      "originX":0.0,
      "originY":0.0,
      "name":"texture_lolratz_takes_a_ride"
    },
    "texture_lolratz_kaideca_emoji":{
      "frames":1.0,
      "prefetch":1.0,
      "file":"emojitest2.png",
      "originX":0.0,
      "originY":0.0,
      "name":"texture_lolratz_kaideca_emoji"
    },
    "texture_lolratz_muck_anim_16":{
      "frames":16.0,
      "prefetch":1.0,
      "file":"spoiler_image (1).png",
      "originX":0.0,
      "originY":0.0,
      "name":"texture_lolratz_muck_anim_16"
    },
    "texture_lolratz_kaideca":{
      "frames":1.0,
      "prefetch":1.0,
      "file":"texture_lolratz_kaideca.jpg",
      "originX":0.0,
      "originY":0.0,
      "name":"texture_lolratz_kaideca"
    },
    "texture_lolratz_muck_anim_8":{
      "frames":8.0,
      "prefetch":1.0,
      "file":"spoiler_image (2).png",
      "originX":0.0,
      "originY":0.0,
      "name":"texture_lolratz_muck_anim_8"
    },
    "texture_lolratz_lost_and_found_family":{
      "frames":1.0,
      "prefetch":1.0,
      "file":"the-lost-and-found-family.png",
      "originX":0.0,
      "originY":0.0,
      "name":"texture_lolratz_lost_and_found_family"
    },
    "texture_lolratz_gabii_emoji":{
      "frames":1.0,
      "prefetch":1.0,
      "file":"1223842012957249566.png",
      "originX":0.0,
      "originY":0.0,
      "name":"texture_lolratz_gabii_emoji"
    },
    "texture_lolratz_mucky2":{
      "frames":1.0,
      "prefetch":1.0,
      "file":"mucky2.png",
      "originX":0.0,
      "originY":0.0,
      "name":"texture_lolratz_mucky2"
    }
  }
}